mkdocs_pycafe/__about__.py
mkdocs_pycafe/__init__.py
mkdocs_pycafe-0.3.0.dist-info/METADATA
mkdocs_pycafe-0.3.0.dist-info/WHEEL
mkdocs_pycafe-0.3.0.dist-info/licenses/LICENSE.txt
mkdocs_pycafe-0.3.0.dist-info/RECORD
